switcheo/Fixed8.py
switcheo/__init__.py
switcheo/authenticated_client.py
switcheo/products.py
switcheo/public_client.py
switcheo/socketio_client.py
switcheo/streaming_client.py
switcheo/switcheo_client.py
switcheo/test_authenticated_client.py
switcheo/test_fixed8.py
switcheo/test_public_client.py
switcheo/test_switcheo_client.py
switcheo/test_switcheo_utils.py
switcheo/utils.py
switcheo/websockets_client.py
switcheo/ethereum/__init__.py
switcheo/ethereum/signatures.py
switcheo/ethereum/utils.py
switcheo/neo/__init__.py
switcheo/neo/signatures.py
switcheo/neo/test_neo_utils.py
switcheo/neo/test_transactions.py
switcheo/neo/transactions.py
switcheo/neo/utils.py
switcheo-0.4.2.dist-info/METADATA
switcheo-0.4.2.dist-info/RECORD
switcheo-0.4.2.dist-info/WHEEL
switcheo-0.4.2.dist-info/top_level.txt
