Metadata-Version: 2.1
Name: switcheo
Version: 0.4.2
Summary: Python Client to interact with the Switcheo Exchange API
Home-page: https://github.com/KeithSSmith/switcheo-python
Author: Keith Smith
Author-email: keith.scotts@gmail.com
License: MIT License
Keywords: switcheo,switcheo-api,trade,ethereum,neo,ETH,NEO,QTUM,client,api,wrapper,exchange,dex,crypto,currency,trading,trading-api
Platform: UNKNOWN
Classifier: Development Status :: 3 - Alpha
Classifier: Intended Audience :: Developers
Classifier: Topic :: Software Development :: Libraries :: Python Modules
Classifier: License :: OSI Approved :: MIT License
Classifier: Natural Language :: English
Classifier: Programming Language :: Python :: 3
Classifier: Programming Language :: Python :: 3.6
Classifier: Programming Language :: Python :: 3.7
Requires-Python: >=3.6
Requires-Dist: neocore (==0.5.6)
Requires-Dist: python-socketio[client] (==4.4.0)
Requires-Dist: requests (==2.22.0)
Requires-Dist: web3 (==5.4.0)
